surface_distance/__init__.py
surface_distance/lookup_tables.py
surface_distance/metrics.py
Surface_Distance_Based_Measures-0.1.dist-info/LICENSE
Surface_Distance_Based_Measures-0.1.dist-info/METADATA
Surface_Distance_Based_Measures-0.1.dist-info/WHEEL
Surface_Distance_Based_Measures-0.1.dist-info/top_level.txt
Surface_Distance_Based_Measures-0.1.dist-info/RECORD
